signledger/__init__.py
signledger/cli.py
signledger/py.typed
signledger/backends/__init__.py
signledger/backends/base.py
signledger/backends/memory.py
signledger/backends/mongodb.py
signledger/backends/postgresql.py
signledger/backends/sqlite.py
signledger/cache/__init__.py
signledger/cache/cache_layer.py
signledger/cli/__init__.py
signledger/compression/__init__.py
signledger/compression/compressor.py
signledger/consensus/__init__.py
signledger/core/__init__.py
signledger/core/batch.py
signledger/core/exceptions.py
signledger/core/ledger.py
signledger/crypto/__init__.py
signledger/crypto/hashing.py
signledger/crypto/merkle.py
signledger/crypto/signatures.py
signledger/distributed/__init__.py
signledger/integrations/__init__.py
signledger/integrations/django.py
signledger/integrations/fastapi.py
signledger/integrations/flask.py
signledger/integrations/django/__init__.py
signledger/integrations/fastapi/__init__.py
signledger/integrations/flask/__init__.py
signledger/pool/__init__.py
signledger/pool/connection_pool.py
signledger/utils/__init__.py
signledger-1.0.0.dist-info/licenses/LICENSE
signledger-1.0.0.dist-info/METADATA
signledger-1.0.0.dist-info/WHEEL
signledger-1.0.0.dist-info/entry_points.txt
signledger-1.0.0.dist-info/top_level.txt
signledger-1.0.0.dist-info/RECORD
