Metadata-Version: 2.4
Name: signledger
Version: 1.0.0
Summary: Immutable audit logging with cryptographic verification for Python applications
Home-page: https://github.com/vipin08/signledger
Author: Vipin Kumar
Author-email: vipin08@example.com
Project-URL: Bug Reports, https://github.com/vipin08/signledger/issues
Project-URL: Source, https://github.com/vipin08/signledger
Keywords: audit logging immutable ledger blockchain cryptography compliance security
Classifier: Development Status :: 5 - Production/Stable
Classifier: Intended Audience :: Developers
Classifier: Topic :: Software Development :: Libraries :: Python Modules
Classifier: Topic :: System :: Logging
Classifier: Topic :: Security :: Cryptography
Classifier: Topic :: Database
Classifier: License :: OSI Approved :: MIT License
Classifier: Programming Language :: Python :: 3
Classifier: Programming Language :: Python :: 3.8
Classifier: Programming Language :: Python :: 3.9
Classifier: Programming Language :: Python :: 3.10
Classifier: Programming Language :: Python :: 3.11
Classifier: Programming Language :: Python :: 3.12
Classifier: Operating System :: OS Independent
Classifier: Typing :: Typed
Requires-Python: >=3.8
License-File: LICENSE
Requires-Dist: pydantic>=2.0.0
Requires-Dist: cryptography>=41.0.0
Requires-Dist: typing-extensions>=4.0.0
Requires-Dist: python-dateutil>=2.8.0
Provides-Extra: postgresql
Requires-Dist: psycopg2-binary>=2.9.0; extra == "postgresql"
Requires-Dist: sqlalchemy>=2.0.0; extra == "postgresql"
Provides-Extra: mongodb
Requires-Dist: pymongo>=4.0.0; extra == "mongodb"
Provides-Extra: sqlite
Requires-Dist: sqlalchemy>=2.0.0; extra == "sqlite"
Provides-Extra: compression
Requires-Dist: zstandard>=0.21.0; extra == "compression"
Requires-Dist: lz4>=4.3.0; extra == "compression"
Provides-Extra: django
Requires-Dist: django>=3.2; extra == "django"
Provides-Extra: flask
Requires-Dist: flask>=2.0.0; extra == "flask"
Provides-Extra: fastapi
Requires-Dist: fastapi>=0.100.0; extra == "fastapi"
Requires-Dist: uvicorn>=0.23.0; extra == "fastapi"
Provides-Extra: async
Requires-Dist: aiofiles>=23.0.0; extra == "async"
Provides-Extra: dev
Requires-Dist: pytest>=7.4.0; extra == "dev"
Requires-Dist: pytest-cov>=4.1.0; extra == "dev"
Requires-Dist: pytest-asyncio>=0.21.0; extra == "dev"
Requires-Dist: pytest-mock>=3.11.0; extra == "dev"
Requires-Dist: black>=23.7.0; extra == "dev"
Requires-Dist: isort>=5.12.0; extra == "dev"
Requires-Dist: flake8>=6.1.0; extra == "dev"
Requires-Dist: mypy>=1.5.0; extra == "dev"
Requires-Dist: bandit>=1.7.5; extra == "dev"
Provides-Extra: test
Requires-Dist: pytest>=7.4.0; extra == "test"
Requires-Dist: pytest-cov>=4.1.0; extra == "test"
Requires-Dist: pytest-asyncio>=0.21.0; extra == "test"
Requires-Dist: pytest-mock>=3.11.0; extra == "test"
Requires-Dist: faker>=19.3.0; extra == "test"
Provides-Extra: all
Requires-Dist: zstandard>=0.21.0; extra == "all"
Requires-Dist: django>=3.2; extra == "all"
Requires-Dist: pymongo>=4.0.0; extra == "all"
Requires-Dist: lz4>=4.3.0; extra == "all"
Requires-Dist: psycopg2-binary>=2.9.0; extra == "all"
Requires-Dist: fastapi>=0.100.0; extra == "all"
Requires-Dist: flask>=2.0.0; extra == "all"
Requires-Dist: uvicorn>=0.23.0; extra == "all"
Requires-Dist: sqlalchemy>=2.0.0; extra == "all"
Requires-Dist: aiofiles>=23.0.0; extra == "all"
Dynamic: author
Dynamic: author-email
Dynamic: classifier
Dynamic: description
Dynamic: description-content-type
Dynamic: home-page
Dynamic: keywords
Dynamic: license-file
Dynamic: project-url
Dynamic: provides-extra
Dynamic: requires-dist
Dynamic: requires-python
Dynamic: summary
